Microfire_SHT3x/Microfire_SHT3x.py
Microfire_SHT3x/__init__.py
Microfire_SHT3x/shell.py
microfire_sht3x-0.9.0.dist-info/METADATA
microfire_sht3x-0.9.0.dist-info/WHEEL
microfire_sht3x-0.9.0.dist-info/licenses/LICENSE
microfire_sht3x-0.9.0.dist-info/RECORD
