Metadata-Version: 2.1
Name: Microfire_SHT3x
Version: 0.9.0
Summary: Measure temperature and humidity with the Sensiron SHT3x sensor. VPD and dew point are also calculated.
Project-URL: Homepage, https://microfire.co
Project-URL: Bug Tracker, https://github.com/u-fire/SHT3x/issues
Author-email: Microfire LLC <contact@microfire.co>
License-File: LICENSE
Classifier: License :: OSI Approved :: MIT License
Classifier: Operating System :: OS Independent
Classifier: Programming Language :: Python :: 3
Requires-Python: >=3.6
